[{
  "_id": {
    "$oid": "600c4a01804d281158c11f71"
  },
  "title": "ptyxiakh",
  "description": "TEI",
  "status": false,
  "task": [
    {
      "title": "task1",
      "completed": false,
      "id": "1"
    },
    {
      "title": "task",
      "completed": true,
      "id": "2"
    },
    {
      "title": "task2",
      "completed": true,
      "id": "3"
    }
  ]
},{
  "_id": {
    "$oid": "600d5a7f0821e90b581073e3"
  },
  "title": "vue app",
  "description": "My first vue js app",
  "status": false,
  "task": [
    {
      "title": "task1",
      "completed": false,
      "id": "1"
    }
  ]
},{
  "_id": {
    "$oid": "600d5a9a0821e90b581073e4"
  },
  "title": "Codeigniter",
  "description": "My first codeigniter app",
  "status": false,
  "task": [
    {
      "title": "task1",
      "completed": false,
      "id": "1"
    },
    {
      "title": "task2",
      "completed": true,
      "id": "2"
    }
  ]
},{
  "_id": {
    "$oid": "600d5ab70821e90b581073e5"
  },
  "title": "Codeigniter_new",
  "description": "My first codeigniter app",
  "status": false,
  "task": [
    {
      "title": "task1",
      "completed": true,
      "id": "1"
    },
    {
      "title": "task2",
      "completed": true,
      "id": "2"
    }
  ]
},{
  "_id": {
    "$oid": "600d5ad50821e90b581073e6"
  },
  "title": "nexctloud",
  "description": "My first codeigniter app",
  "status": false,
  "task": [
    {
      "title": "task1",
      "completed": true,
      "id": "1"
    },
    {
      "title": "task2",
      "completed": true,
      "id": "2"
    },
    {
      "title": "task2",
      "completed": true,
      "id": "3"
    }
  ]
}]